recmetrics_new/__init__.py
recmetrics_new/metrics.py
recmetrics_new/plots.py
recmetrics_new-0.3.1.dist-info/LICENSE
recmetrics_new-0.3.1.dist-info/WHEEL
recmetrics_new-0.3.1.dist-info/METADATA
recmetrics_new-0.3.1.dist-info/RECORD
