Metadata-Version: 2.1
Name: recmetrics-new
Version: 0.3.1
Summary: A library of metrics for evaluating recommender systems
Author: Daniil Smirnov
Author-email: den762000@mail.ru
Requires-Python: >=3.6.1,<4.0.0
Classifier: Programming Language :: Python :: 3
Classifier: Programming Language :: Python :: 3.7
Classifier: Programming Language :: Python :: 3.8
Classifier: Programming Language :: Python :: 3.9
Requires-Dist: funcsigs (>=1.0.2,<2.0.0)
Requires-Dist: matplotlib (>=3.3.2,<4.0.0)
Requires-Dist: pandas (>=1.1.5,<2.0.0)
Requires-Dist: plotly (>=4.11.0,<5.0.0)
Requires-Dist: pytest-cov (>=2.10.1,<3.0.0)
Requires-Dist: scikit-learn (>=0.23.2,<0.24.0)
Requires-Dist: scikit-surprise (>=1.1.1,<2.0.0)
Requires-Dist: scipy (>=1.5.2,<2.0.0)
Requires-Dist: seaborn (>=0.11.0,<0.12.0)
